{
  "type": "FeatureCollection",
  "features": [
    {
      "type": "Feature",
      "properties": {
        "name": "Nowhere Cafe",
        "address": "339/2c Lê Văn Sỹ, Phường 14, Quận 3, Thành phố Hồ Chí Minh",
        "instagram": "nowherecafe.official",
        "open_time": "Mon - Sun, 7:00 - 22:00",
        "wifi_speed": "25 Mbps",
        "proposed_price": "≥35.000₫",
        "image": "https://images2.imgbox.com/de/3a/rX1oXFkg_o.jpg",
        "marker-color": "#50C240",
        "marker-symbol": "cafe"
      },
      "geometry": {
        "type": "Point",
        "coordinates": [
          106.67710597863223,
          10.787868659193846
        ]
      }
    },
    {
      "type": "Feature",
      "properties": {
        "name": "Caramew cafe",
        "address": "108/26A Trần Quang Diệu, Phường 14, Quận 3, Thành phố Hồ Chí Minh",
        "instagram": "caramewcafe",
        "open_time": "Mon - Sun, 7:00 - 21:30",
        "wifi_speed": "25 Mbps",
        "proposed_price": "45.000₫",
        "image": "https://images2.imgbox.com/89/f5/mDJXDilL_o.jpg",
        "marker-color": "#50C240",
        "marker-symbol": "cafe"
      },
      "geometry": {
        "type": "Point",
        "coordinates": [
          106.68016981186432,
          10.790363292902166
        ]
      }
    },
    {
      "type": "Feature",
      "properties": {
        "name": "The Seat Cafe",
        "address": "491/2 Lê Văn Sỹ, Phường 12, Quận 3, Thành phố Hồ Chí Minh",
        "instagram": "theseatcafe",
        "open_time": "Mon - Sun, 8:00 - 22:30",
        "wifi_speed": "25 Mbps",
        "proposed_price": "32.000₫",
        "image": "https://images2.imgbox.com/36/2a/JrsZrTR9_o.jpg",
        "marker-color": "#50C240",
        "marker-symbol": "cafe"
      },
      "geometry": {
        "type": "Point",
        "coordinates": [
          106.67375875655647,
          10.790082616475091
        ]
      }
    }
  ]
}
